MelissaData-0.1.dist-info/DESCRIPTION.rst
MelissaData-0.1.dist-info/METADATA
MelissaData-0.1.dist-info/RECORD
MelissaData-0.1.dist-info/WHEEL
MelissaData-0.1.dist-info/metadata.json
MelissaData-0.1.dist-info/top_level.txt
melissadata/__init__.py
melissadata/melissadata.py
