Metadata-Version: 2.0
Name: MelissaData
Version: 0.1
Summary: A Python interface for MelissaData JSON API
Home-page: https://github.com/gregmccoy/melissadata
Author: Greg McCoy
Author-email: gregmccoy@gfa.org
License: MIT
Platform: UNKNOWN
